nhspy/__init__.py
nhspy/nhspy.py
nhspy-0.1.0.dist-info/DESCRIPTION.rst
nhspy-0.1.0.dist-info/METADATA
nhspy-0.1.0.dist-info/metadata.json
nhspy-0.1.0.dist-info/RECORD
nhspy-0.1.0.dist-info/top_level.txt
nhspy-0.1.0.dist-info/WHEEL
