Metadata-Version: 2.0
Name: nhspy
Version: 0.1.0
Summary: A python package to help with NHS-specific functions.
Home-page: https://github.com/mattstibbs/nhspy
Author: Matt Stibbs
Author-email: nhs-py@stibbsy.co.uk
License: ISCL
Keywords: nhspy
Platform: UNKNOWN
Classifier: Development Status :: 2 - Pre-Alpha
Classifier: Intended Audience :: Developers
Classifier: License :: OSI Approved :: ISC License (ISCL)
Classifier: Natural Language :: English
Classifier: Programming Language :: Python :: 2
Classifier: Programming Language :: Python :: 2.6
Classifier: Programming Language :: Python :: 2.7
Classifier: Programming Language :: Python :: 3
Classifier: Programming Language :: Python :: 3.3
Classifier: Programming Language :: Python :: 3.4
Classifier: Programming Language :: Python :: 3.5
